{
  "version": 1,
  "skills": {
    "design-taste-frontend": {
      "source": "Leonxlnx/taste-skill",
      "sourceType": "github",
      "skillPath": "skills/taste-skill/SKILL.md",
      "computedHash": "6d838b246d0e35d0b53f4f23f98ba7a1dd561937e64f7d0c7553b0928e376c3e"
    },
    "transitions-dev": {
      "source": "Jakubantalik/transitions.dev",
      "sourceType": "github",
      "skillPath": "skills/transitions-dev/SKILL.md",
      "computedHash": "3849b47b846e2d49935487799c6eb9340dcfe3c1defb2e93fbc59d18df589af2"
    }
  }
}
